{
	"miniprogramRoot": "miniprogram/",
	"cloudfunctionRoot": "cloudfunctions/",
	"setting": {
		"urlCheck": true,
		"es6": true,
		"postcss": true,
		"minified": true,
		"newFeature": true,
		"enhance": true
	},
	"appid": "wx8defb5b19d50417c",
	"projectname": "%E5%8C%BB%E5%AD%A6%E8%80%83%E7%82%B9%E9%9A%8F%E6%97%B6%E8%AE%B0",
	"libVersion": "2.8.1",
	"simulatorType": "wechat",
	"simulatorPluginLibVersion": {},
	"condition": {
		"search": {
			"current": -1,
			"list": []
		},
		"conversation": {
			"current": -1,
			"list": []
		},
		"plugin": {
			"current": -1,
			"list": []
		},
		"game": {
			"list": []
		},
		"gamePlugin": {
			"current": -1,
			"list": []
		},
		"miniprogram": {
			"current": -1,
			"list": [
				{
					"id": -1,
					"name": "db guide",
					"pathName": "pages/databaseGuide/databaseGuide",
					"query": ""
				},
				{
					"id": 1,
					"name": "首页",
					"pathName": "pages/home/home/home",
					"query": "",
					"scene": null
				},
				{
					"id": 2,
					"name": "技能",
					"pathName": "pages/skill/skill/skill",
					"query": "",
					"scene": null
				},
				{
					"id": 3,
					"name": "练习",
					"pathName": "pages/test/test/test",
					"query": "",
					"scene": null
				},
				{
					"id": 4,
					"name": "关于",
					"pathName": "pages/about/about/about",
					"query": "",
					"scene": null
				},
				{
					"id": -1,
					"name": "程序日志",
					"pathName": "pages/about/log/log",
					"query": "",
					"scene": null
				},
				{
					"id": -1,
					"name": "习题页",
					"pathName": "pages/test/one1/one1",
					"query": "",
					"scene": null
				},
				{
					"id": -1,
					"name": "个人收藏页面",
					"pathName": "pages/about/favor/favor",
					"query": "",
					"scene": null
				},
				{
					"id": -1,
					"name": "小程序信息",
					"pathName": "pages/about/info/info",
					"query": "",
					"scene": null
				},
				{
					"id": -1,
					"name": "设置",
					"pathName": "pages/about/setting/setting",
					"query": "",
					"scene": null
				},
				{
					"id": -1,
					"name": "pages/home/homeDetail/homeDetail",
					"pathName": "pages/home/homeDetail/homeDetail",
					"query": "",
					"scene": null
				}
			]
		}
	}
}